ha.v
module half_adder(sum,carry,a,b);
input a,b;
output sum,carry;
xor g1(sum,a,b);
and g2(carry,a,b);
endmodule

fa.v
module full_adder_join(fsum,fcarry_out,a,b,c);
input a,b,c;
output fsum,fcarry_out;
wire half_sum_1,half_carry_1,half_carry_2;
half_adder g1(half_sum_1,half_carry_1,a,b);
half_adder g2(fsum,half_carry_2,half_sum_1,c);
or g3(fcarry_out,half_carry_1,half_carry_2);
endmodule

tb_fulladder_ha.v
`timescale 1ns / 1ns 
module full_adder_2_HA_tb; 
wire t_out_sum, t_out_carry; 
reg t_a, t_b, t_c; 
full_adder_join my_full_adder(.a(t_a), .b(t_b), .c(t_c), .fsum(t_out_sum), .fcarry_out(t_out_carry)); 
initial 
begin
 $dumpfile("fulladder_ha.vcd");
         $dumpvars;
 // 1 
t_a = 1'b0; 
t_b = 1'b0; 
t_c = 1'b0;
#5 //2 
t_a = 1'b0; 
t_b = 1'b0; 
t_c = 1'b1;
#5 //3 
t_a = 1'b0; 
t_b = 1'b1; 
t_c = 1'b0;
#5 //4 
t_a = 1'b0; 
t_b = 1'b1; 
t_c = 1'b1;
#5 //5 
t_a = 1'b1; 
t_b = 1'b0; 
t_c = 1'b0;
#5 //6 
t_a = 1'b1; 
t_b = 1'b0; 
t_c = 1'b1;
#5 //7 
t_a = 1'b1; 
t_b = 1'b1; 
t_c = 1'b0;
#5 //8
t_a = 1'b1; 
t_b = 1'b1; 
t_c = 1'b1;
end 
endmodule

fulladder_ha.vcd
$date
	Sun Aug 25 20:38:33 2019
$end
$version
	Icarus Verilog
$end
$timescale
	1ns
$end
$scope module full_adder_2_HA_tb $end
$var wire 1 ! t_out_carry $end
$var wire 1 " t_out_sum $end
$var reg 1 # t_a $end
$var reg 1 $ t_b $end
$var reg 1 % t_c $end
$scope module my_full_adder $end
$var wire 1 & a $end
$var wire 1 ' b $end
$var wire 1 ( c $end
$var wire 1 ! fcarry_out $end
$var wire 1 " fsum $end
$var wire 1 ) half_carry_1 $end
$var wire 1 * half_carry_2 $end
$var wire 1 + half_sum_1 $end
$scope module g1 $end
$var wire 1 & a $end
$var wire 1 ' b $end
$var wire 1 ) carry $end
$var wire 1 + sum $end
$upscope $end
$scope module g2 $end
$var wire 1 + a $end
$var wire 1 ( b $end
$var wire 1 * carry $end
$var wire 1 " sum $end
$upscope $end
$upscope $end
$upscope $end
$enddefinitions $end
#0
$dumpvars
0+
0*
0)
0(
0'
0&
0%
0$
0#
0"
0!
$end
#5
1"
1%
1(
#10
1+
0%
0(
1$
1'
#15
1!
0"
1*
1%
1(
#20
0!
1"
0*
0%
0(
0$
0'
1#
1&
#25
1!
0"
1*
1%
1(
#30
0*
0+
1)
0%
0(
1$
1'
#35
1"
1%
1(
